bonsai_cli/__init__.py
bonsai_cli/aad.py
bonsai_cli/api.py
bonsai_cli/application_insights.py
bonsai_cli/config.py
bonsai_cli/cookies.py
bonsai_cli/exceptions.py
bonsai_cli/logger.py
bonsai_cli/utils.py
bonsai_cli/commands/__init__.py
bonsai_cli/commands/assessment.py
bonsai_cli/commands/bonsai.py
bonsai_cli/commands/brain.py
bonsai_cli/commands/brain_version.py
bonsai_cli/commands/dataset.py
bonsai_cli/commands/dataset_aml.py
bonsai_cli/commands/deployment.py
bonsai_cli/commands/deployment_webapp.py
bonsai_cli/commands/exportedbrain.py
bonsai_cli/commands/imported_model.py
bonsai_cli/commands/simulator.py
bonsai_cli/commands/simulator_package.py
bonsai_cli/commands/simulator_package_container.py
bonsai_cli/commands/simulator_package_modelfile.py
bonsai_cli/commands/simulator_unmanaged.py
bonsai_cli/commands/workspace.py
bonsai_cli/commands/diaglets/__init__.py
bonsai_cli/commands/diaglets/container_restarts.py
bonsai_cli/commands/diaglets/diaglet_base.py
bonsai_cli/commands/diaglets/diaglet_configuration.py
bonsai_cli/commands/diaglets/episode_logs_enabled.py
bonsai_cli/commands/diaglets/error_messages.py
bonsai_cli/commands/diaglets/iteration_halted.py
bonsai_cli/commands/diaglets/last_n_records.py
bonsai_cli/commands/diaglets/sdk_version.py
bonsai_cli/commands/diaglets/sim_timeout.py
bonsai_cli/commands/diaglets/sys_logs_enabled.py
bonsai_cli-1.0.19.dist-info/LICENSE
bonsai_cli-1.0.19.dist-info/METADATA
bonsai_cli-1.0.19.dist-info/WHEEL
bonsai_cli-1.0.19.dist-info/entry_points.txt
bonsai_cli-1.0.19.dist-info/top_level.txt
bonsai_cli-1.0.19.dist-info/RECORD
